setup.py
pympl/__init__.py
pympl/client.py
pympl/email.py
pympl/exc.py
pympl/function.py
pympl/requeststring.py
pympl/resolvers.py
pympl/storedproc.py
pympl/table.py
pympl/types.py
python_mp.egg-info/PKG-INFO
python_mp.egg-info/SOURCES.txt
python_mp.egg-info/dependency_links.txt
python_mp.egg-info/requires.txt
python_mp.egg-info/top_level.txt