Metadata-Version: 1.0
Name: python-mp
Version: 0.1.2
Summary: Python bindings for Ministry Platform
Home-page: http://docs.fun.blackpulp.com/pympl
Author: Tim Radke
Author-email: tim@blackpulp.com
License: UNKNOWN
Platform: UNKNOWN
